[
    {
        "name": "Liberty PWE 5107 W",
        "link": "https://hotline.ua/ua/bt-kuhonnye-plity-i-poverhnosti/liberty-pwe-5107/",
        "price_range": "9 919 – 10 876 грн",
        "shop_count": 10,
        "shops": [
            {
                "shop_name": "Comtrading.ua",
                "price": "10 281 гpн"
            },
            {
                "shop_name": "ФОКСТРОТ",
                "price": "9 919 гpн"
            },
            {
                "shop_name": "ЭЛМАГ",
                "price": "10 864 гpн"
            },
            {
                "shop_name": "ELMIR.UA",
                "price": "10 876 гpн"
            },
            {
                "shop_name": "TehnoAge",
                "price": "9 919 гpн"
            },
            {
                "shop_name": "DiDi",
                "price": "10 375 гpн"
            },
            {
                "shop_name": "ТЕХНОСТАР",
                "price": "10 458 гpн"
            },
            {
                "shop_name": "STOREinUA",
                "price": "10 286 гpн"
            },
            {
                "shop_name": "Элдом",
                "price": "10 794 гpн"
            },
            {
                "shop_name": "Setevuha",
                "price": "10 323 гpн"
            }
        ]
    },
    {
        "name": "Hansa FCMW53050",
        "link": "https://hotline.ua/ua/bt-kuhonnye-plity-i-poverhnosti/hansa-fcmw53050/",
        "price_range": "10 470 – 11 730 грн",
        "shop_count": 13,
        "shops": [
            {
                "shop_name": "TEHNOS.UA",
                "price": "11 730 гpн"
            },
            {
                "shop_name": "TENDO.com.ua",
                "price": "10 481 гpн"
            },
            {
                "shop_name": "Кухня",
                "price": "11 367 гpн"
            },
            {
                "shop_name": "DENIKA.UA",
                "price": "11 354 гpн"
            },
            {
                "shop_name": "FoRoom",
                "price": "10 777 гpн"
            },
            {
                "shop_name": "Інтернет магазин OpenShop",
                "price": "10 590 гpн"
            },
            {
                "shop_name": "TOPTV",
                "price": "10 600 гpн"
            },
            {
                "shop_name": "AVIC",
                "price": "11 000 гpн"
            },
            {
                "shop_name": "Tehnopostavka",
                "price": "10 700 гpн"
            },
            {
                "shop_name": "Дешевле Нет",
                "price": "11 718 гpн"
            },
            {
                "shop_name": "Элдом",
                "price": "11 256 гpн"
            },
            {
                "shop_name": "Сенюшко",
                "price": "10 470 гpн"
            },
            {
                "shop_name": "Techno-Geek",
                "price": "10 500 гpн"
            }
        ]
    },
    {
        "name": "Hansa FCEW53001",
        "link": "https://hotline.ua/ua/bt-kuhonnye-plity-i-poverhnosti/hansa-fcew53001/",
        "price_range": "10 499 – 12 702 грн",
        "shop_count": 22,
        "shops": [
            {
                "shop_name": "ЭЛМАГ",
                "price": "11 767 гpн"
            },
            {
                "shop_name": "Леруа Мерлен Україна",
                "price": "12 499 гpн"
            },
            {
                "shop_name": "Кухня",
                "price": "11 269 гpн"
            },
            {
                "shop_name": "ALLO.ua",
                "price": "10 499 гpн"
            },
            {
                "shop_name": "TENDO.com.ua",
                "price": "11 021 гpн"
            },
            {
                "shop_name": "ТЕХНОточка",
                "price": "11 767 гpн"
            },
            {
                "shop_name": "DENIKA.UA",
                "price": "10 800 гpн"
            },
            {
                "shop_name": "FoRoom",
                "price": "11 241 гpн"
            },
            {
                "shop_name": "DiDi",
                "price": "11 039 гpн"
            },
            {
                "shop_name": "Інтернет магазин OpenShop",
                "price": "11 031 гpн"
            },
            {
                "shop_name": "Техномастер",
                "price": "11 649 гpн"
            },
            {
                "shop_name": "Enko",
                "price": "11 330 гpн"
            },
            {
                "shop_name": "Tehnopostavka",
                "price": "11 498 гpн"
            },
            {
                "shop_name": "BTMax",
                "price": "10 911 гpн"
            },
            {
                "shop_name": "Дешевле Нет",
                "price": "11 407 гpн"
            },
            {
                "shop_name": "STOREinUA",
                "price": "12 702 гpн"
            },
            {
                "shop_name": "Элдом",
                "price": "12 600 гpн"
            },
            {
                "shop_name": "Технофаворит",
                "price": "10 815 гpн"
            },
            {
                "shop_name": "ТопТехник",
                "price": "11 124 гpн"
            },
            {
                "shop_name": "Твій Дім",
                "price": "11 594 гpн"
            },
            {
                "shop_name": "Комплект",
                "price": "11 556 гpн"
            },
            {
                "shop_name": "POBOOT.com.ua",
                "price": "12 189 гpн"
            }
        ]
    },
    {
        "name": "SMEG TR93BL",
        "link": "https://hotline.ua/ua/bt-kuhonnye-plity-i-poverhnosti/smeg-tr93bl/",
        "price_range": "134 287 – 236 500 грн",
        "shop_count": 10,
        "shops": [
            {
                "shop_name": "SMG-SHOP",
                "price": "199 000 гpн"
            },
            {
                "shop_name": "SMG-SHOP",
                "price": "236 500 гpн"
            },
            {
                "shop_name": "SMGLINE",
                "price": "199 000 гpн"
            },
            {
                "shop_name": "SMGLINE",
                "price": "236 500 гpн"
            },
            {
                "shop_name": "eBox24.biz",
                "price": "153 001 гpн"
            },
            {
                "shop_name": "Electrone",
                "price": "134 633 гpн"
            },
            {
                "shop_name": "TehnoExpert",
                "price": "154 818 гpн"
            },
            {
                "shop_name": "Voltyk.com.ua",
                "price": "134 297 гpн"
            },
            {
                "shop_name": "redimal.in.ua",
                "price": "134 287 гpн"
            },
            {
                "shop_name": "Smeg.net.ua",
                "price": "175 827 гpн"
            }
        ]
    }
]